qmp.py
qmp-1.0.0.dist-info/LICENSE
qmp-1.0.0.dist-info/METADATA
qmp-1.0.0.dist-info/WHEEL
qmp-1.0.0.dist-info/top_level.txt
qmp-1.0.0.dist-info/RECORD
