Metadata-Version: 2.1
Name: qmp
Version: 1.0.0
Summary: QEMU Machine Protocol client
Author-email: QEMU Project <qemu-devel@nongnu.org>
Maintainer-email: Alexey Bogdanenko <alexey@bogdanenko.com>
Project-URL: Homepage, https://gitlab.com/abogdanenko/qmp
Classifier: Development Status :: 5 - Production/Stable
Classifier: Intended Audience :: Developers
Classifier: License :: OSI Approved :: GNU General Public License v2 (GPLv2)
Classifier: Operating System :: POSIX :: Linux
Classifier: Programming Language :: Python :: 3
Classifier: Programming Language :: Python :: 3.6
Classifier: Programming Language :: Python :: 3.7
Classifier: Programming Language :: Python :: 3.8
Classifier: Programming Language :: Python :: 3.9
Classifier: Programming Language :: Python :: 3.10
Classifier: Programming Language :: Python :: 3.11
Classifier: Programming Language :: Python :: 3 :: Only
Requires-Python: >=3.6
License-File: LICENSE
